AUTHORS.rst
CONTRIBUTING.rst
LICENSE
MANIFEST.in
README.rst
setup.cfg
setup.py
django_qurl_templatetag.egg-info/PKG-INFO
django_qurl_templatetag.egg-info/SOURCES.txt
django_qurl_templatetag.egg-info/dependency_links.txt
django_qurl_templatetag.egg-info/not-zip-safe
django_qurl_templatetag.egg-info/top_level.txt
docs/Makefile
docs/authors.rst
docs/conf.py
docs/contributing.rst
docs/index.rst
docs/installation.rst
docs/make.bat
docs/readme.rst
docs/usage.rst
qurl_templatetag/__init__.py
qurl_templatetag/qurl.py
qurl_templatetag/templatetags/__init__.py
qurl_templatetag/templatetags/qurl.py
tests/__init__.py
tests/test_qurl_templatetag.py