Metadata-Version: 1.1
Name: django-qurl-templatetag
Version: 0.0.14
Summary: A Django template tag to modify url's query string.
Home-page: https://github.com/sophilabs/django-qurl-templatetag
Author: Sophilabs
Author-email: hi@sophilabs.com
License: MIT license
Keywords: django,templatetag
Platform: UNKNOWN
Classifier: Development Status :: 2 - Pre-Alpha
Classifier: Intended Audience :: Developers
Classifier: License :: OSI Approved :: MIT License
Classifier: Natural Language :: English
Classifier: Programming Language :: Python :: 3.4
Classifier: Programming Language :: Python :: 3.5
Classifier: Programming Language :: Python :: 3.6
Classifier: Programming Language :: Python :: 3.7
Classifier: Programming Language :: Python :: 3.8
